{
  "_id": "6a69f3bd5082fa7a",
  "name": "Community Larder Key",
  "type": "consumable",
  "img": "icons/svg/item-bag.svg",
  "system": {
    "description": "<p>Key to a community food and supply cache. Forge Tender's community network access token.</p>",
    "charges": 1,
    "maxCharges": 1,
    "cardMods": []
  },
  "effects": [],
  "flags": {
    "tesshari": {
      "sourceId": "community_larder_key",
      "originalCategory": "gear"
    }
  },
  "folder": null,
  "sort": 0,
  "ownership": {
    "default": 0
  }
}