{
  "_id": "b6323c2bd2e5c9d7",
  "_key": "!items!b6323c2bd2e5c9d7",
  "name": "Puppet Screen",
  "type": "card",
  "img": "icons/svg/combat.svg",
  "system": {
    "tier": 1,
    "apCost": 1,
    "baseDamage": 0,
    "pierce": 0,
    "category": "defense",
    "primaryStat": "",
    "keywords": [
      "Guard 6 + SIGNAL"
    ],
    "unlockLevel": 1,
    "className": "Puppet Binder",
    "subclass": "",
    "isRaceCard": false,
    "race": "",
    "isStartingHand": false,
    "isReaction": false,
    "usesPerCombat": null,
    "description": "<p>Direct your active vessel to intercept the next attack targeting you or one ally within 20 feet this round. Reduce incoming damage by 6 + SIGNAL. The vessel takes the reduced damage instead.</p>"
  },
  "effects": [],
  "flags": {
    "tesshari": {
      "sourceId": "card_puppet_binder_puppet_screen",
      "enrichedFromMarkdown": true
    }
  },
  "folder": null,
  "sort": 1001,
  "ownership": {
    "default": 0
  }
}