{
  "_id": "fcf0c9c65c857d6b",
  "_key": "!items!fcf0c9c65c857d6b",
  "name": "Honed Cut",
  "type": "card",
  "img": "icons/svg/combat.svg",
  "system": {
    "tier": 1,
    "apCost": 1,
    "baseDamage": 0,
    "pierce": 0,
    "category": "utility",
    "primaryStat": "",
    "keywords": [],
    "unlockLevel": 1,
    "className": "Ronin",
    "subclass": "Ronin — Ascendant Blade",
    "isRaceCard": false,
    "race": "",
    "isStartingHand": false,
    "isReaction": false,
    "usesPerCombat": null,
    "description": "<p>A strike refined by ten thousand solitary repetitions. Precision-weighted EDGE attack; treats armor as thinner than it is.</p>"
  },
  "effects": [],
  "flags": {
    "tesshari": {
      "sourceId": "card_ronin_ascendant_blade_honed_cut",
      "enrichedFromMarkdown": false
    }
  },
  "folder": null,
  "sort": 1001,
  "ownership": {
    "default": 0
  }
}