{
  "_id": "2df928f62542b20d",
  "_key": "!items!2df928f62542b20d",
  "name": "Find the Hole",
  "type": "card",
  "img": "icons/svg/combat.svg",
  "system": {
    "tier": 1,
    "apCost": 1,
    "baseDamage": 0,
    "pierce": 0,
    "category": "passive",
    "primaryStat": "",
    "keywords": [],
    "unlockLevel": 2,
    "className": "Ashfoot",
    "subclass": "",
    "isRaceCard": false,
    "race": "",
    "isStartingHand": false,
    "isReaction": false,
    "usesPerCombat": null,
    "description": "<p>You have learned to read enhancement armor for its actual gaps rather than its advertised coverage. Your attacks ignore 2 points of Guard on all targets. Against targets with no enhancement armor at all, your attacks deal + IRON additional damage instead.</p>"
  },
  "effects": [],
  "flags": {
    "tesshari": {
      "sourceId": "card_ashfoot_find_the_hole",
      "enrichedFromMarkdown": true
    }
  },
  "folder": null,
  "sort": 1002,
  "ownership": {
    "default": 0
  }
}