{
  "_id": "27826841af3a00b5",
  "name": "Oath Edge",
  "type": "card",
  "img": "icons/svg/combat.svg",
  "system": {
    "tier": 1,
    "apCost": 1,
    "baseDamage": 6,
    "pierce": 0,
    "category": "attack",
    "primaryStat": "iron",
    "keywords": [],
    "unlockLevel": 1,
    "className": "Ironclad Samurai",
    "subclass": "",
    "isRaceCard": false,
    "race": "",
    "isStartingHand": false,
    "isReaction": false,
    "usesPerCombat": null,
    "description": "<p>A measured, committed strike — form-perfect. Deal 6 + IRON damage. If you have not moved this turn, add RESONANCE to the damage. The code rewards stillness.</p>"
  },
  "effects": [],
  "flags": {
    "tesshari": {
      "sourceId": "card_ironclad_oath_edge"
    }
  },
  "folder": null,
  "sort": 1001,
  "ownership": {
    "default": 0
  }
}