{
  "_id": "6527465835da4a6e",
  "_key": "!items!6527465835da4a6e",
  "name": "Vein Strike",
  "type": "card",
  "img": "icons/svg/combat.svg",
  "system": {
    "tier": 1,
    "apCost": 1,
    "baseDamage": 6,
    "pierce": 0,
    "category": "attack",
    "primaryStat": "iron",
    "keywords": [],
    "unlockLevel": 1,
    "className": "Ironclad Samurai",
    "subclass": "",
    "isRaceCard": false,
    "race": "",
    "isStartingHand": true,
    "isReaction": false,
    "usesPerCombat": null,
    "description": "<p>A disciplined blow that carries the weight of your oath. Deal 6 + IRON damage. Once per turn, if this is the first card you played this turn, add RESONANCE to the damage.</p>"
  },
  "effects": [],
  "flags": {
    "tesshari": {
      "sourceId": "card_ironclad_vein_strike",
      "enrichedFromMarkdown": true
    }
  },
  "folder": null,
  "sort": 1001,
  "ownership": {
    "default": 0
  }
}