{
  "_id": "ac5164f15b5628d1",
  "_key": "!items!ac5164f15b5628d1",
  "name": "Thread Whisper",
  "type": "card",
  "img": "icons/svg/combat.svg",
  "system": {
    "tier": 0,
    "apCost": 0,
    "baseDamage": 0,
    "pierce": 0,
    "category": "utility",
    "primaryStat": "",
    "keywords": [],
    "unlockLevel": 1,
    "className": "Puppet Binder",
    "subclass": "",
    "isRaceCard": false,
    "race": "",
    "isStartingHand": false,
    "isReaction": false,
    "usesPerCombat": null,
    "description": "<p>Send a quiet command down a binding thread to a creature you control. It takes one simple free-action instruction (drop item, speak a word, look left, open hand) at its next opportunity without its allies noticing.</p>"
  },
  "effects": [],
  "flags": {
    "tesshari": {
      "sourceId": "card_puppet_binder_thread_whisper",
      "enrichedFromMarkdown": false
    }
  },
  "folder": null,
  "sort": 1,
  "ownership": {
    "default": 0
  }
}