{
  "_id": "d9185b0d406459c7",
  "name": "Void Procession",
  "type": "card",
  "img": "icons/svg/combat.svg",
  "system": {
    "tier": 3,
    "apCost": 4,
    "baseDamage": 0,
    "pierce": 0,
    "category": "utility",
    "primaryStat": "",
    "keywords": [],
    "unlockLevel": 1,
    "className": "Ironclad Samurai",
    "subclass": "Ironclad Samurai — Oath Sutensai Blade",
    "isRaceCard": false,
    "race": "",
    "isStartingHand": false,
    "isReaction": false,
    "usesPerCombat": null,
    "description": "<p>Step fully into the between for six seconds. You are invisible and incorporeal; the first melee attack you make upon returning is an automatic critical that severs one class feature of the target until it completes a long rest.</p>"
  },
  "effects": [],
  "flags": {
    "tesshari": {
      "sourceId": "card_ironclad_oath_sutensai_blade_void_procession"
    }
  },
  "folder": null,
  "sort": 3000,
  "ownership": {
    "default": 0
  }
}