{
  "_id": "a42295b29a378d2b",
  "_key": "!items!a42295b29a378d2b",
  "name": "Whisper of the Dead",
  "type": "card",
  "img": "icons/svg/combat.svg",
  "system": {
    "tier": 0,
    "apCost": 0,
    "baseDamage": 0,
    "pierce": 0,
    "category": "utility",
    "primaryStat": "",
    "keywords": [],
    "unlockLevel": 1,
    "className": "Fracture Knight",
    "subclass": "Fracture Knight — Haunted Legion",
    "isRaceCard": false,
    "race": "",
    "isStartingHand": false,
    "isReaction": false,
    "usesPerCombat": null,
    "description": "<p>A slain knight murmurs the next stroke to you. Gain advantage on your next RESONANCE check or attack; if you miss, the whisper keeps for one round.</p>"
  },
  "effects": [],
  "flags": {
    "tesshari": {
      "sourceId": "card_fracture_knight_haunted_legion_whisper_of_the_dead",
      "enrichedFromMarkdown": false
    }
  },
  "folder": null,
  "sort": 1,
  "ownership": {
    "default": 0
  }
}