{
  "_id": "3e27ea08a1886541",
  "name": "Reflex Carapace",
  "type": "card",
  "img": "icons/svg/combat.svg",
  "system": {
    "tier": 2,
    "apCost": 2,
    "baseDamage": 0,
    "pierce": 0,
    "category": "utility",
    "primaryStat": "",
    "keywords": [],
    "unlockLevel": 1,
    "className": "Chrome Shaper",
    "subclass": "Chrome Shaper — War Shaper",
    "isRaceCard": false,
    "race": "",
    "isStartingHand": false,
    "isReaction": false,
    "usesPerCombat": null,
    "description": "<p>Your skin reads the battlefield before your mind does. The first attack against you this round has disadvantage; if it misses, the attacker takes 1d4 + FRAME damage. Once per short rest.</p>"
  },
  "effects": [],
  "flags": {
    "tesshari": {
      "sourceId": "card_chrome_shaper_war_shaper_reflex_carapace"
    }
  },
  "folder": null,
  "sort": 2000,
  "ownership": {
    "default": 0
  }
}